Workbook
Name Slicer_Region: #N/A

Sheet Pivot_Analysis
A3: Row Labels | B3: Sum of Revenue | C3: Sum of Profit
A4: Aarav Sharma | B4: 274804.54 | C4: 76865.54
A5: Diya Patel | B5: 264212.3 | C5: 75656.08
A6: Rohan Mehta | B6: 262705.6 | C6: 79368.55
A7: Kabir Shah | B7: 315763.03 | C7: 93632.99
A8: Ananya Singh | B8: 230719.42 | C8: 70162.21
A9: Meera Iyer | B9: 220346.25 | C9: 63607
A10: Grand Total | B10: 1568551.1 | C10: 459292.37

Sheet Trend_Analysis
A3: Row Labels | B3: Sum of Revenue
A4: 2025 | B4: 1568551.1
A5: Jan | B5: 171519.03
A6: Feb | B6: 130421.46
A7: Mar | B7: 111334.26
A8: Apr | B8: 135516.08
A9: May | B9: 110195.22
A10: Jun | B10: 81732.4
A11: Jul | B11: 161144.96
A12: Aug | B12: 166164.42
A13: Sep | B13: 151028.03
A14: Oct | B14: 110986.31
A15: Nov | B15: 116185.74
... A17: Grand Total | B17: 1568551.1

Sheet Category_Analysis
A3: Row Labels | B3: Sum of Revenue | C3: Sum of Profit
A4: Accessories | B4: 70999.42 | C4: 20736.27
A5: Laptops | B5: 844947.87 | C5: 248787.74
A6: Monitors | B6: 339576.38 | C6: 99655.57
A7: Printers | B7: 313027.47 | C7: 90112.79
A8: Grand Total | B8: 1568551.1 | C8: 459292.37

Sheet Region_Analysis
A3: Row Labels | B3: Sum of Revenue
A4: East | B4: 419782.95
A5: North | B5: 405818.46
A6: South | B6: 370097.3
A7: West | B7: 372852.43
A8: Grand Total | B8: 1568551.1

Sheet SalesRep_Analysis
A3: Row Labels | B3: Sum of Revenue | C3: Sum of Profit
A4: Aarav Sharma | B4: 274804.54 | C4: 76865.54
A5: Ananya Singh | B5: 230719.42 | C5: 70162.21
A6: Diya Patel | B6: 264212.3 | C6: 75656.08
A7: Kabir Shah | B7: 315763.03 | C7: 93632.99
A8: Meera Iyer | B8: 220346.25 | C8: 63607
A9: Rohan Mehta | B9: 262705.6 | C9: 79368.55
A10: Grand Total | B10: 1568551.1 | C10: 459292.37

Sheet Sales_Data
A1: Order_ID | B1: Order_Date | C1: Region | D1: Sales_Rep | E1: Customer | F1: Channel | G1: Category | H1: Product | I1: Units | J1: Unit_Price | K1: Discount | L1: Revenue | M1: Cost | N1: Target | O1: Standard_Price | P1: Profit | Q1: Profit_Margin | R1: Target_Variance | S1: Target_Status
A2: ORD1001 | B2: 45823 | C2: North | D2: Kabir Shah | E2: Customer 028 | F2: Online | G2: Laptops | H2: Business 13 | I2: 7 | J2: 964.34 | K2: 0 | L2: 6750.38 | M2: 5269.89 | N2: 6092.83 | O2: =_xlfn.XLOOKUP(SalesData[[#This Row],[Product]],ProductLookup[Product],ProductLookup[Standard_Price],"Not Found") -> 950 | P2: =SalesData[[#This Row],[Revenue]]-SalesData[[#This Row],[Cost]] -> 1480.49 | Q2: =IFERROR(SalesData[[#This Row],[Profit]]/SalesData[[#This Row],[Revenue]],0) -> 0.2193195 | R2: =SalesData[[#This Row],[Revenue]]-SalesData[[#This Row],[Target]] -> 657.55 | S2: =IF(R2>=0,"Above Target","Below Target") -> Above Target
A3: ORD1002 | B3: 45702 | C3: North | D3: Diya Patel | E3: Customer 081 | F3: Online | G3: Accessories | H3: Wireless Mouse | I3: 7 | J3: 33.49 | K3: 0 | L3: 234.43 | M3: 169.08 | N3: 209.62 | O3: =_xlfn.XLOOKUP(SalesData[[#This Row],[Product]],ProductLookup[Product],ProductLookup[Standard_Price],"Not Found") -> 35 | P3: =SalesData[[#This Row],[Revenue]]-SalesData[[#This Row],[Cost]] -> 65.35 | Q3: =IFERROR(SalesData[[#This Row],[Profit]]/SalesData[[#This Row],[Revenue]],0) -> 0.27876125 | R3: =SalesData[[#This Row],[Revenue]]-SalesData[[#This Row],[Target]] -> 24.81 | S3: =IF(R3>=0,"Above Target","Below Target") -> Above Target
A4: ORD1003 | B4: 45953 | C4: East | D4: Ananya Singh | E4: Customer 019 | F4: Online | G4: Accessories | H4: Webcam HD | I4: 7 | J4: 71.62 | K4: 0.02 | L4: 491.31 | M4: 299.82 | N4: 533.58 | O4: =_xlfn.XLOOKUP(SalesData[[#This Row],[Product]],ProductLookup[Product],ProductLookup[Standard_Price],"Not Found") -> 75 | P4: =SalesData[[#This Row],[Revenue]]-SalesData[[#This Row],[Cost]] -> 191.49 | Q4: =IFERROR(SalesData[[#This Row],[Profit]]/SalesData[[#This Row],[Revenue]],0) -> 0.38975392 | R4: =SalesData[[#This Row],[Revenue]]-SalesData[[#This Row],[Target]] -> -42.27 | S4: =IF(R4>=0,"Above Target","Below Target") -> Below Target
A5: ORD1004 | B5: 45950 | C5: South | D5: Rohan Mehta | E5: Customer 013 | F5: Online | G5: Monitors | H5: Monitor 27 | I5: 9 | J5: 330.12 | K5: 0.02 | L5: 2911.66 | M5: 1813.01 | N5: 2961.42 | O5: =_xlfn.XLOOKUP(SalesData[[#This Row],[Product]],ProductLookup[Product],ProductLookup[Standard_Price],"Not Found") -> 320 | P5: =SalesData[[#This Row],[Revenue]]-SalesData[[#This Row],[Cost]] -> 1098.65 | Q5: =IFERROR(SalesData[[#This Row],[Profit]]/SalesData[[#This Row],[Revenue]],0) -> 0.37732771 | R5: =SalesData[[#This Row],[Revenue]]-SalesData[[#This Row],[Target]] -> -49.76 | S5: =IF(R5>=0,"Above Target","Below Target") -> Below Target
A6: ORD1005 | B6: 45946 | C6: West | D6: Kabir Shah | E6: Customer 119 | F6: Corporate | G6: Laptops | H6: ProBook 14 | I6: 10 | J6: 825.01 | K6: 0.1 | L6: 7425.09 | M6: 5323.63 | N6: 7919.12 | O6: =_xlfn.XLOOKUP(SalesData[[#This Row],[Product]],ProductLookup[Product],ProductLookup[Standard_Price],"Not Found") -> 850 | P6: =SalesData[[#This Row],[Revenue]]-SalesData[[#This Row],[Cost]] -> 2101.46 | Q6: =IFERROR(SalesData[[#This Row],[Profit]]/SalesData[[#This Row],[Revenue]],0) -> 0.28302149 | R6: =SalesData[[#This Row],[Revenue]]-SalesData[[#This Row],[Target]] -> -494.03 | S6: =IF(R6>=0,"Above Target","Below Target") -> Below Target
A7: ORD1006 | B7: 45843 | C7: East | D7: Kabir Shah | E7: Customer 064 | F7: Distributor | G7: Monitors | H7: Monitor 27 | I7: 4 | J7: 329.42 | K7: 0.1 | L7: 1185.91 | M7: 915 | N7: 1066.9 | O7: =_xlfn.XLOOKUP(SalesData[[#This Row],[Product]],ProductLookup[Product],ProductLookup[Standard_Price],"Not Found") -> 320 | P7: =SalesData[[#This Row],[Revenue]]-SalesData[[#This Row],[Cost]] -> 270.91 | Q7: =IFERROR(SalesData[[#This Row],[Profit]]/SalesData[[#This Row],[Revenue]],0) -> 0.22844061 | R7: =SalesData[[#This Row],[Revenue]]-SalesData[[#This Row],[Target]] -> 119.01 | S7: =IF(R7>=0,"Above Target","Below Target") -> Above Target
A8: ORD1007 | B8: 45887 | C8: East | D8: Diya Patel | E8: Customer 120 | F8: Corporate | G8: Monitors | H8: Monitor 27 | I8: 10 | J8: 335.37 | K8: 0 | L8: 3353.7 | M8: 2389.93 | N8: 3084.03 | O8: =_xlfn.XLOOKUP(SalesData[[#This Row],[Product]],ProductLookup[Product],ProductLookup[Standard_Price],"Not Found") -> 320 | P8: =SalesData[[#This Row],[Revenue]]-SalesData[[#This Row],[Cost]] -> 963.77 | Q8: =IFERROR(SalesData[[#This Row],[Profit]]/SalesData[[#This Row],[Revenue]],0) -> 0.28737514 | R8: =SalesData[[#This Row],[Revenue]]-SalesData[[#This Row],[Target]] -> 269.67 | S8: =IF(R8>=0,"Above Target","Below Target") -> Above Target
A9: ORD1008 | B9: 45873 | C9: East | D9: Rohan Mehta | E9: Customer 089 | F9: Distributor | G9: Laptops | H9: ProBook 14 | I9: 11 | J9: 814.1 | K9: 0.08 | L9: 8238.69 | M9: 5981.83 | N9: 8981.12 | O9: =_xlfn.XLOOKUP(SalesData[[#This Row],[Product]],ProductLookup[Product],ProductLookup[Standard_Price],"Not Found") -> 850 | P9: =SalesData[[#This Row],[Revenue]]-SalesData[[#This Row],[Cost]] -> 2256.86 | Q9: =IFERROR(SalesData[[#This Row],[Profit]]/SalesData[[#This Row],[Revenue]],0) -> 0.27393433 | R9: =SalesData[[#This Row],[Revenue]]-SalesData[[#This Row],[Target]] -> -742.43 | S9: =IF(R9>=0,"Above Target","Below Target") -> Below Target
A10: ORD1009 | B10: 45962 | C10: West | D10: Meera Iyer | E10: Customer 086 | F10: Online | G10: Accessories | H10: Mechanical Keyboard | I10: 10 | J10: 87.52 | K10: 0 | L10: 875.2 | M10: 686.85 | N10: 968.6 | O10: =_xlfn.XLOOKUP(SalesData[[#This Row],[Product]],ProductLookup[Product],ProductLookup[Standard_Price],"Not Found") -> 85 | P10: =SalesData[[#This Row],[Revenue]]-SalesData[[#This Row],[Cost]] -> 188.35 | Q10: =IFERROR(SalesData[[#This Row],[Profit]]/SalesData[[#This Row],[Revenue]],0) -> 0.21520795 | R10: =SalesData[[#This Row],[Revenue]]-SalesData[[#This Row],[Target]] -> -93.4 | S10: =IF(R10>=0,"Above Target","Below Target") -> Below Target
A11: ORD1010 | B11: 45689 | C11: East | D11: Meera Iyer | E11: Customer 050 | F11: Distributor | G11: Printers | H11: OfficeJet Pro | I11: 12 | J11: 333.53 | K11: 0.08 | L11: 3682.17 | M11: 3013.79 | N11: 3966.66 | O11: =_xlfn.XLOOKUP(SalesData[[#This Row],[Product]],ProductLookup[Product],ProductLookup[Standard_Price],"Not Found") -> 340 | P11: =SalesData[[#This Row],[Revenue]]-SalesData[[#This Row],[Cost]] -> 668.38 | Q11: =IFERROR(SalesData[[#This Row],[Profit]]/SalesData[[#This Row],[Revenue]],0) -> 0.18151796 | R11: =SalesData[[#This Row],[Revenue]]-SalesData[[#This Row],[Target]] -> -284.49 | S11: =IF(R11>=0,"Above Target","Below Target") -> Below Target
A12: ORD1011 | B12: 45669 | C12: East | D12: Diya Patel | E12: Customer 095 | F12: Retail | G12: Accessories | H12: Mechanical Keyboard | I12: 6 | J12: 82.18 | K12: 0 | L12: 493.08 | M12: 349.4 | N12: 459.73 | O12: =_xlfn.XLOOKUP(SalesData[[#This Row],[Product]],ProductLookup[Product],ProductLookup[Standard_Price],"Not Found") -> 85 | P12: =SalesData[[#This Row],[Revenue]]-SalesData[[#This Row],[Cost]] -> 143.68 | Q12: =IFERROR(SalesData[[#This Row],[Profit]]/SalesData[[#This Row],[Revenue]],0) -> 0.29139288 | R12: =SalesData[[#This Row],[Revenue]]-SalesData[[#This Row],[Target]] -> 33.35 | S12: =IF(R12>=0,"Above Target","Below Target") -> Above Target
A13: ORD1012 | B13: 45861 | C13: East | D13: Diya Patel | E13: Customer 105 | F13: Corporate | G13: Accessories | H13: Wireless Mouse | I13: 15 | J13: 36.3 | K13: 0 | L13: 544.5 | M13: 346.63 | N13: 531.65 | O13: =_xlfn.XLOOKUP(SalesData[[#This Row],[Product]],ProductLookup[Product],ProductLookup[Standard_Price],"Not Found") -> 35 | P13: =SalesData[[#This Row],[Revenue]]-SalesData[[#This Row],[Cost]] -> 197.87 | Q13: =IFERROR(SalesData[[#This Row],[Profit]]/SalesData[[#This Row],[Revenue]],0) -> 0.36339761 | R13: =SalesData[[#This Row],[Revenue]]-SalesData[[#This Row],[Target]] -> 12.85 | S13: =IF(R13>=0,"Above Target","Below Target") -> Above Target
... A501: ORD1500 | B501: 45672 | C501: South | D501: Diya Patel | E501: Customer 023 | F501: Distributor | G501: Laptops | H501: UltraBook 15 | I501: 13 | J501: 1045.52 | K501: 0.02 | L501: 13319.92 | M501: 8243.32 | N501: 12517.27 | O501: =_xlfn.XLOOKUP(SalesData[[#This Row],[Product]],ProductLookup[Product],ProductLookup[Standard_Price],"Not Found") -> 1100 | P501: =SalesData[[#This Row],[Revenue]]-SalesData[[#This Row],[Cost]] -> 5076.6 | Q501: =IFERROR(SalesData[[#This Row],[Profit]]/SalesData[[#This Row],[Revenue]],0) -> 0.38112842 | R501: =SalesData[[#This Row],[Revenue]]-SalesData[[#This Row],[Target]] -> 802.65 | S501: =IF(R501>=0,"Above Target","Below Target") -> Above Target

Sheet Sales_MIS_Practice_Data_500_Row
A1: Order_ID | B1: Order_Date | C1: Region | D1: Sales_Rep | E1: Customer | F1: Channel | G1: Category | H1: Product | I1: Units | J1: Unit_Price | K1: Discount | L1: Revenue | M1: Cost | N1: Target
A2: ORD1001 | B2: 45823 | C2: North | D2: Kabir Shah | E2: Customer 028 | F2: Online | G2: Laptops | H2: Business 13 | I2: 7 | J2: 964.34 | K2: 0 | L2: 6750.38 | M2: 5269.89 | N2: 6092.83
A3: ORD1002 | B3: 45702 | C3: North | D3: Diya Patel | E3: Customer 081 | F3: Online | G3: Accessories | H3: Wireless Mouse | I3: 7 | J3: 33.49 | K3: 0 | L3: 234.43 | M3: 169.08 | N3: 209.62
A4: ORD1003 | B4: 45953 | C4: East | D4: Ananya Singh | E4: Customer 019 | F4: Online | G4: Accessories | H4: Webcam HD | I4: 7 | J4: 71.62 | K4: 0.02 | L4: 491.31 | M4: 299.82 | N4: 533.58
A5: ORD1004 | B5: 45950 | C5: South | D5: Rohan Mehta | E5: Customer 013 | F5: Online | G5: Monitors | H5: Monitor 27 | I5: 9 | J5: 330.12 | K5: 0.02 | L5: 2911.66 | M5: 1813.01 | N5: 2961.42
A6: ORD1005 | B6: 45946 | C6: West | D6: Kabir Shah | E6: Customer 119 | F6: Corporate | G6: Laptops | H6: ProBook 14 | I6: 10 | J6: 825.01 | K6: 0.1 | L6: 7425.09 | M6: 5323.63 | N6: 7919.12
A7: ORD1006 | B7: 45843 | C7: East | D7: Kabir Shah | E7: Customer 064 | F7: Distributor | G7: Monitors | H7: Monitor 27 | I7: 4 | J7: 329.42 | K7: 0.1 | L7: 1185.91 | M7: 915 | N7: 1066.9
A8: ORD1007 | B8: 45887 | C8: East | D8: Diya Patel | E8: Customer 120 | F8: Corporate | G8: Monitors | H8: Monitor 27 | I8: 10 | J8: 335.37 | K8: 0 | L8: 3353.7 | M8: 2389.93 | N8: 3084.03
A9: ORD1008 | B9: 45873 | C9: East | D9: Rohan Mehta | E9: Customer 089 | F9: Distributor | G9: Laptops | H9: ProBook 14 | I9: 11 | J9: 814.1 | K9: 0.08 | L9: 8238.69 | M9: 5981.83 | N9: 8981.12
A10: ORD1009 | B10: 45962 | C10: West | D10: Meera Iyer | E10: Customer 086 | F10: Online | G10: Accessories | H10: Mechanical Keyboard | I10: 10 | J10: 87.52 | K10: 0 | L10: 875.2 | M10: 686.85 | N10: 968.6
A11: ORD1010 | B11: 45689 | C11: East | D11: Meera Iyer | E11: Customer 050 | F11: Distributor | G11: Printers | H11: OfficeJet Pro | I11: 12 | J11: 333.53 | K11: 0.08 | L11: 3682.17 | M11: 3013.79 | N11: 3966.66
A12: ORD1011 | B12: 45669 | C12: East | D12: Diya Patel | E12: Customer 095 | F12: Retail | G12: Accessories | H12: Mechanical Keyboard | I12: 6 | J12: 82.18 | K12: 0 | L12: 493.08 | M12: 349.4 | N12: 459.73
A13: ORD1012 | B13: 45861 | C13: East | D13: Diya Patel | E13: Customer 105 | F13: Corporate | G13: Accessories | H13: Wireless Mouse | I13: 15 | J13: 36.3 | K13: 0 | L13: 544.5 | M13: 346.63 | N13: 531.65
... A501: ORD1500 | B501: 45672 | C501: South | D501: Diya Patel | E501: Customer 023 | F501: Distributor | G501: Laptops | H501: UltraBook 15 | I501: 13 | J501: 1045.52 | K501: 0.02 | L501: 13319.92 | M501: 8243.32 | N501: 12517.27

Sheet Raw_Import

Sheet KPI_Report
A1: KPI | B1: Value
A2: Total Revenue | B2: =SUM(SalesData[Revenue]) -> 1568551.1
A3: Total Profit | B3: =SUM(SalesData[Profit]) -> 459292.37
A4: Profit Margin | B4: =IFERROR(B3/B2,0) -> 0.29281313
A5: Target Achievement | B5: =IFERROR(SUM(SalesData[Revenue])/SUM(SalesData[Target]),0) -> 0.99833536
A6: Total Units Sold | B6: =SUM(SalesData[Units]) -> 4156
A7: Below Target Transactions | B7: =COUNTIF(SalesData[Target_Status],"Below Target") -> 256

Sheet Lookup_Lists
A1: Product | B1: Category | C1: Standard_Price | D1: Target_Multiplier
A2: ProBook 14 | B2: Laptops | C2: 850 | D2: 1.05
A3: UltraBook 15 | B3: Laptops | C3: 1100 | D3: 1.08
A4: Business 13 | B4: Laptops | C4: 950 | D4: 1.06
A5: Monitor 24 | B5: Monitors | C5: 220 | D5: 1.04
A6: Monitor 27 | B6: Monitors | C6: 320 | D6: 1.05
A7: Monitor 32 | B7: Monitors | C7: 450 | D7: 1.06
A8: Wireless Mouse | B8: Accessories | C8: 35 | D8: 1.03
A9: Mechanical Keyboard | B9: Accessories | C9: 85 | D9: 1.04
A10: USB-C Hub | B10: Accessories | C10: 60 | D10: 1.03
A11: Webcam HD | B11: Accessories | C11: 75 | D11: 1.04
A12: LaserJet M200 | B12: Printers | C12: 260 | D12: 1.05
A13: OfficeJet Pro | B13: Printers | C13: 340 | D13: 1.06
A14: ColorJet X | B14: Printers | C14: 420 | D14: 1.07

Sheet Dashboard
A1: SALES MIS DASHBOARD – 2025
A3: TOTAL REVENUE | B3: TOTAL PROFIT | C3: PROFIT MARGIN | D3: TARGET ACHIEVEMENT
A4: =KPI_Report!B2 -> 1568551.1 | B4: =KPI_Report!B3 -> 459292.37 | C4: =KPI_Report!B4 -> 0.29281313 | D4: =KPI_Report!B5 -> 0.99833536
A7: TOTAL UNITS SOLD | C7: BELOW-TARGET TRANSACTIONS
A8: =KPI_Report!B6 -> 4156 | C8: =KPI_Report!B7 -> 256
A42: MANAGEMENT INSIGHTS
A43: Laptops are the highest-revenue category at ₹844,947.87.
A44: East is the highest-revenue region at ₹419,782.95.
A45: Kabir Shah is the top sales representative by revenue at ₹315,763.03.
A46: June is the lowest-revenue month at ₹81,732.40.
